Metadata-Version: 2.1
Name: llama-index-indices-managed-dashscope-custom
Version: 0.1.1
Summary: llama-index indices managed-dashscope integration
License: MIT
Author: Ruixue Ding
Author-email: ada.drx@alibaba-inc.com
Requires-Python: >=3.8.1,<4.0
Classifier: License :: OSI Approved :: MIT License
Classifier: Programming Language :: Python :: 3
Classifier: Programming Language :: Python :: 3.9
Classifier: Programming Language :: Python :: 3.10
Classifier: Programming Language :: Python :: 3.11
Classifier: Programming Language :: Python :: 3.12
Requires-Dist: llama-index-core (>=0.10.0,<0.11.0)
Requires-Dist: llama-index-embeddings-dashscope (>=0.1.3)
Requires-Dist: llama-index-node-parser-dashscope-custom (>=0.1.2)
Requires-Dist: llama-index-readers-dashscope-custom (>=0.1.1)
